aura/__init__.py
aura/api.py
aura/config.py
aura/exceptions.py
aura/session.py
aura/utils.py
aura_api-1.0.4.dist-info/LICENSE
aura_api-1.0.4.dist-info/METADATA
aura_api-1.0.4.dist-info/WHEEL
aura_api-1.0.4.dist-info/top_level.txt
aura_api-1.0.4.dist-info/RECORD
