Metadata-Version: 2.1
Name: aura-api
Version: 1.0.4
Summary: Python API for Yandex.Aura
Home-page: https://github.com/skorpionikus/aura-api
Author: mickxolotl
Author-email: mickxolotl@yandex.ru
License: GPL3
Keywords: yandex aura api
Platform: UNKNOWN
Requires-Dist: requests
